prepdatakit/__init__.py
prepdatakit/prepdatakit.py
prepdatakit-1.5.8.dist-info/METADATA
prepdatakit-1.5.8.dist-info/WHEEL
prepdatakit-1.5.8.dist-info/top_level.txt
prepdatakit-1.5.8.dist-info/RECORD
