Metadata-Version: 2.1
Name: prepdatakit
Version: 1.5.8
Summary: A comprehensive toolkit for preprocessing datasets, including data reading, data summary generation, handling missing values, and categorical data encoding.
Author: Abdulaziz Mofid
Author-email: abdulaziz.mofid@gmail.com
Classifier: Programming Language :: Python :: 3
Classifier: License :: OSI Approved :: MIT License
Classifier: Operating System :: OS Independent
Requires-Python: >=3.6
Requires-Dist: scikit-learn ==1.2.1
Requires-Dist: numpy ==1.23.5
Requires-Dist: pandas ==1.4.2
Requires-Dist: tabulate ==0.9.0
